webes
